{
  "node": {
    "003bdb41977fafc385b089ea1b1a363d738935fdfc": {
      "workers": {
        "app/page": {
          "moduleId": 43675,
          "async": false,
          "exportedName": "getTrades",
          "filename": "app/actions/trade-actions.ts"
        },
        "app/reports/page": {
          "moduleId": 45006,
          "async": false,
          "exportedName": "getTrades",
          "filename": "app/actions/trade-actions.ts"
        },
        "app/trades/[id]/page": {
          "moduleId": 41705,
          "async": false,
          "exportedName": "getTrades",
          "filename": "app/actions/trade-actions.ts"
        },
        "app/trades/page": {
          "moduleId": 55249,
          "async": false,
          "exportedName": "getTrades",
          "filename": "app/actions/trade-actions.ts"
        }
      },
      "layer": {
        "app/page": "rsc",
        "app/reports/page": "rsc",
        "app/trades/[id]/page": "rsc",
        "app/trades/page": "rsc"
      },
      "filename": "app/actions/trade-actions.ts",
      "exportedName": "getTrades"
    },
    "404d76a0830acf0ac4288e23290c039cbd3c7de1ce": {
      "workers": {
        "app/page": {
          "moduleId": 43675,
          "async": false,
          "exportedName": "getTrade",
          "filename": "app/actions/trade-actions.ts"
        },
        "app/reports/page": {
          "moduleId": 45006,
          "async": false,
          "exportedName": "getTrade",
          "filename": "app/actions/trade-actions.ts"
        },
        "app/trades/[id]/page": {
          "moduleId": 41705,
          "async": false,
          "exportedName": "getTrade",
          "filename": "app/actions/trade-actions.ts"
        },
        "app/trades/page": {
          "moduleId": 55249,
          "async": false,
          "exportedName": "getTrade",
          "filename": "app/actions/trade-actions.ts"
        }
      },
      "layer": {
        "app/page": "rsc",
        "app/reports/page": "rsc",
        "app/trades/[id]/page": "rsc",
        "app/trades/page": "rsc"
      },
      "filename": "app/actions/trade-actions.ts",
      "exportedName": "getTrade"
    },
    "40a6cc6f1f2178696141d579a69bfb77252b4d97f8": {
      "workers": {
        "app/page": {
          "moduleId": 43675,
          "async": false,
          "exportedName": "createTrade",
          "filename": "app/actions/trade-actions.ts"
        },
        "app/reports/page": {
          "moduleId": 45006,
          "async": false,
          "exportedName": "createTrade",
          "filename": "app/actions/trade-actions.ts"
        },
        "app/trades/[id]/page": {
          "moduleId": 41705,
          "async": false,
          "exportedName": "createTrade",
          "filename": "app/actions/trade-actions.ts"
        },
        "app/trades/page": {
          "moduleId": 55249,
          "async": false,
          "exportedName": "createTrade",
          "filename": "app/actions/trade-actions.ts"
        }
      },
      "layer": {
        "app/page": "action-browser",
        "app/reports/page": "rsc",
        "app/trades/[id]/page": "rsc",
        "app/trades/page": "rsc"
      },
      "filename": "app/actions/trade-actions.ts",
      "exportedName": "createTrade"
    },
    "40ff44ff1593cccb6762fa1dfdda55b4f154bce892": {
      "workers": {
        "app/page": {
          "moduleId": 43675,
          "async": false,
          "exportedName": "deleteTrade",
          "filename": "app/actions/trade-actions.ts"
        },
        "app/reports/page": {
          "moduleId": 45006,
          "async": false,
          "exportedName": "deleteTrade",
          "filename": "app/actions/trade-actions.ts"
        },
        "app/trades/[id]/page": {
          "moduleId": 41705,
          "async": false,
          "exportedName": "deleteTrade",
          "filename": "app/actions/trade-actions.ts"
        },
        "app/trades/page": {
          "moduleId": 55249,
          "async": false,
          "exportedName": "deleteTrade",
          "filename": "app/actions/trade-actions.ts"
        }
      },
      "layer": {
        "app/page": "rsc",
        "app/reports/page": "rsc",
        "app/trades/[id]/page": "rsc",
        "app/trades/page": "rsc"
      },
      "filename": "app/actions/trade-actions.ts",
      "exportedName": "deleteTrade"
    },
    "60ebe67b8ff8ece876c43cb6478d274e72270a4de9": {
      "workers": {
        "app/page": {
          "moduleId": 43675,
          "async": false,
          "exportedName": "updateTrade",
          "filename": "app/actions/trade-actions.ts"
        },
        "app/reports/page": {
          "moduleId": 45006,
          "async": false,
          "exportedName": "updateTrade",
          "filename": "app/actions/trade-actions.ts"
        },
        "app/trades/[id]/page": {
          "moduleId": 41705,
          "async": false,
          "exportedName": "updateTrade",
          "filename": "app/actions/trade-actions.ts"
        },
        "app/trades/page": {
          "moduleId": 55249,
          "async": false,
          "exportedName": "updateTrade",
          "filename": "app/actions/trade-actions.ts"
        }
      },
      "layer": {
        "app/page": "rsc",
        "app/reports/page": "rsc",
        "app/trades/[id]/page": "action-browser",
        "app/trades/page": "rsc"
      },
      "filename": "app/actions/trade-actions.ts",
      "exportedName": "updateTrade"
    },
    "4042d9d02b006aeba0d0c1abce59f22ed3757dd9f9": {
      "workers": {
        "app/notebook/page": {
          "moduleId": 11947,
          "async": false,
          "exportedName": "createNote",
          "filename": "app/actions/note-actions.ts"
        },
        "app/page": {
          "moduleId": 43675,
          "async": false,
          "exportedName": "createNote",
          "filename": "app/actions/note-actions.ts"
        }
      },
      "layer": {
        "app/notebook/page": "action-browser",
        "app/page": "action-browser"
      },
      "filename": "app/actions/note-actions.ts",
      "exportedName": "createNote"
    },
    "0083eb236ecd51927952cda1a88f01b78b44944c75": {
      "workers": {
        "app/notebook/page": {
          "moduleId": 11947,
          "async": false,
          "exportedName": "getSections",
          "filename": "app/actions/note-actions.ts"
        },
        "app/page": {
          "moduleId": 43675,
          "async": false,
          "exportedName": "getSections",
          "filename": "app/actions/note-actions.ts"
        }
      },
      "layer": {
        "app/notebook/page": "rsc",
        "app/page": "action-browser"
      },
      "filename": "app/actions/note-actions.ts",
      "exportedName": "getSections"
    },
    "40265b30102208e2dbfd12633e96636836ce67eda6": {
      "workers": {
        "app/page": {
          "moduleId": 43675,
          "async": false,
          "exportedName": "createCategory",
          "filename": "app/actions/tag-actions.ts"
        },
        "app/reports/page": {
          "moduleId": 45006,
          "async": false,
          "exportedName": "createCategory",
          "filename": "app/actions/tag-actions.ts"
        },
        "app/tags/page": {
          "moduleId": 48624,
          "async": false,
          "exportedName": "createCategory",
          "filename": "app/actions/tag-actions.ts"
        },
        "app/trades/[id]/page": {
          "moduleId": 41705,
          "async": false,
          "exportedName": "createCategory",
          "filename": "app/actions/tag-actions.ts"
        }
      },
      "layer": {
        "app/page": "action-browser",
        "app/reports/page": "rsc",
        "app/tags/page": "action-browser",
        "app/trades/[id]/page": "rsc"
      },
      "filename": "app/actions/tag-actions.ts",
      "exportedName": "createCategory"
    },
    "406890b07abd01545dd838dd5e595466dd49672ebd": {
      "workers": {
        "app/page": {
          "moduleId": 43675,
          "async": false,
          "exportedName": "createTag",
          "filename": "app/actions/tag-actions.ts"
        },
        "app/reports/page": {
          "moduleId": 45006,
          "async": false,
          "exportedName": "createTag",
          "filename": "app/actions/tag-actions.ts"
        },
        "app/tags/page": {
          "moduleId": 48624,
          "async": false,
          "exportedName": "createTag",
          "filename": "app/actions/tag-actions.ts"
        },
        "app/trades/[id]/page": {
          "moduleId": 41705,
          "async": false,
          "exportedName": "createTag",
          "filename": "app/actions/tag-actions.ts"
        }
      },
      "layer": {
        "app/page": "action-browser",
        "app/reports/page": "rsc",
        "app/tags/page": "action-browser",
        "app/trades/[id]/page": "rsc"
      },
      "filename": "app/actions/tag-actions.ts",
      "exportedName": "createTag"
    },
    "401b3aa34ac0439e0024b2b923778bf44edb922d4d": {
      "workers": {
        "app/notebook/page": {
          "moduleId": 11947,
          "async": false,
          "exportedName": "createTemplate",
          "filename": "app/actions/template-actions.ts"
        },
        "app/page": {
          "moduleId": 43675,
          "async": false,
          "exportedName": "createTemplate",
          "filename": "app/actions/template-actions.ts"
        }
      },
      "layer": {
        "app/notebook/page": "action-browser",
        "app/page": "action-browser"
      },
      "filename": "app/actions/template-actions.ts",
      "exportedName": "createTemplate"
    },
    "0012b0fb54d7c60fda7355e278d2c327c63a247960": {
      "workers": {
        "app/notebook/page": {
          "moduleId": 11947,
          "async": false,
          "exportedName": "getNotes",
          "filename": "app/actions/note-actions.ts"
        }
      },
      "layer": {
        "app/notebook/page": "rsc"
      },
      "filename": "app/actions/note-actions.ts",
      "exportedName": "getNotes"
    },
    "40fc2a295eb212a4a8f487ac6d38f293db05c0d210": {
      "workers": {
        "app/notebook/page": {
          "moduleId": 11947,
          "async": false,
          "exportedName": "deleteNote",
          "filename": "app/actions/note-actions.ts"
        }
      },
      "layer": {
        "app/notebook/page": "action-browser"
      },
      "filename": "app/actions/note-actions.ts",
      "exportedName": "deleteNote"
    },
    "6062f86ae61a00969d4a1203d25a3ad253f9f0ac06": {
      "workers": {
        "app/notebook/page": {
          "moduleId": 11947,
          "async": false,
          "exportedName": "updateNote",
          "filename": "app/actions/note-actions.ts"
        }
      },
      "layer": {
        "app/notebook/page": "action-browser"
      },
      "filename": "app/actions/note-actions.ts",
      "exportedName": "updateNote"
    },
    "00a5501a00bacef6ebba6b41499ec193739cbce65b": {
      "workers": {
        "app/notebook/page": {
          "moduleId": 11947,
          "async": false,
          "exportedName": "getTemplates",
          "filename": "app/actions/template-actions.ts"
        }
      },
      "layer": {
        "app/notebook/page": "action-browser"
      },
      "filename": "app/actions/template-actions.ts",
      "exportedName": "getTemplates"
    },
    "60a791547e0eff38717b00b69518f77fbeb1e939c2": {
      "workers": {
        "app/notebook/page": {
          "moduleId": 11947,
          "async": false,
          "exportedName": "updateTemplate",
          "filename": "app/actions/template-actions.ts"
        }
      },
      "layer": {
        "app/notebook/page": "action-browser"
      },
      "filename": "app/actions/template-actions.ts",
      "exportedName": "updateTemplate"
    },
    "40d18498003e55a4d84f21a5deed2dac65f4675d9d": {
      "workers": {
        "app/notebook/page": {
          "moduleId": 11947,
          "async": false,
          "exportedName": "deleteTemplate",
          "filename": "app/actions/template-actions.ts"
        }
      },
      "layer": {
        "app/notebook/page": "action-browser"
      },
      "filename": "app/actions/template-actions.ts",
      "exportedName": "deleteTemplate"
    },
    "0053c2991b153a5bfd651fb43ef45a92e50dedd5aa": {
      "workers": {
        "app/reports/page": {
          "moduleId": 45006,
          "async": false,
          "exportedName": "getCategories",
          "filename": "app/actions/tag-actions.ts"
        },
        "app/tags/page": {
          "moduleId": 48624,
          "async": false,
          "exportedName": "getCategories",
          "filename": "app/actions/tag-actions.ts"
        },
        "app/trades/[id]/page": {
          "moduleId": 41705,
          "async": false,
          "exportedName": "getCategories",
          "filename": "app/actions/tag-actions.ts"
        }
      },
      "layer": {
        "app/reports/page": "rsc",
        "app/tags/page": "rsc",
        "app/trades/[id]/page": "rsc"
      },
      "filename": "app/actions/tag-actions.ts",
      "exportedName": "getCategories"
    },
    "40483b3fa33e4e7224b9332c539e22dffe6158a91c": {
      "workers": {
        "app/reports/page": {
          "moduleId": 45006,
          "async": false,
          "exportedName": "deleteTag",
          "filename": "app/actions/tag-actions.ts"
        },
        "app/tags/page": {
          "moduleId": 48624,
          "async": false,
          "exportedName": "deleteTag",
          "filename": "app/actions/tag-actions.ts"
        },
        "app/trades/[id]/page": {
          "moduleId": 41705,
          "async": false,
          "exportedName": "deleteTag",
          "filename": "app/actions/tag-actions.ts"
        }
      },
      "layer": {
        "app/reports/page": "rsc",
        "app/tags/page": "action-browser",
        "app/trades/[id]/page": "rsc"
      },
      "filename": "app/actions/tag-actions.ts",
      "exportedName": "deleteTag"
    },
    "40a11be9358d3ebe9de33ae0c86d1ada70bf8b7562": {
      "workers": {
        "app/reports/page": {
          "moduleId": 45006,
          "async": false,
          "exportedName": "deleteCategory",
          "filename": "app/actions/tag-actions.ts"
        },
        "app/tags/page": {
          "moduleId": 48624,
          "async": false,
          "exportedName": "deleteCategory",
          "filename": "app/actions/tag-actions.ts"
        },
        "app/trades/[id]/page": {
          "moduleId": 41705,
          "async": false,
          "exportedName": "deleteCategory",
          "filename": "app/actions/tag-actions.ts"
        }
      },
      "layer": {
        "app/reports/page": "rsc",
        "app/tags/page": "action-browser",
        "app/trades/[id]/page": "rsc"
      },
      "filename": "app/actions/tag-actions.ts",
      "exportedName": "deleteCategory"
    },
    "6027cde55327f090e4abf24830ed1af39fdc545367": {
      "workers": {
        "app/reports/page": {
          "moduleId": 45006,
          "async": false,
          "exportedName": "updateCategory",
          "filename": "app/actions/tag-actions.ts"
        },
        "app/tags/page": {
          "moduleId": 48624,
          "async": false,
          "exportedName": "updateCategory",
          "filename": "app/actions/tag-actions.ts"
        },
        "app/trades/[id]/page": {
          "moduleId": 41705,
          "async": false,
          "exportedName": "updateCategory",
          "filename": "app/actions/tag-actions.ts"
        }
      },
      "layer": {
        "app/reports/page": "rsc",
        "app/tags/page": "action-browser",
        "app/trades/[id]/page": "rsc"
      },
      "filename": "app/actions/tag-actions.ts",
      "exportedName": "updateCategory"
    }
  },
  "edge": {},
  "encryptionKey": "hAU3lUyCGUCa+zzzKBtkgokdw64fIDrdEW3ys9opOHI="
}